[
  {
    "id": 1,
    "country": "Japan",
    "capital": "Tokyo",
    "population": 125800000,
    "interesting_fact": "Japan has more than 6,800 islands."
  },
  {
    "id": 2,
    "country": "Brazil",
    "capital": "Brasília",
    "population": 203100000,
    "interesting_fact": "The Amazon Rainforest produces about 20% of the world's oxygen."
  },
  {
    "id": 3,
    "country": "Canada",
    "capital": "Ottawa",
    "population": 38900000,
    "interesting_fact": "Canada has the longest coastline in the world."
  },
  {
    "id": 4,
    "country": "Australia",
    "capital": "Canberra",
    "population": 26700000,
    "interesting_fact": "Australia is home to more kangaroos than people."
  },
  {
    "id": 5,
    "country": "Germany",
    "capital": "Berlin",
    "population": 83200000,
    "interesting_fact": "Germany has over 1,500 types of sausages."
  },
  {
    "id": 6,
    "country": "India",
    "capital": "New Delhi",
    "population": 1428000000,
    "interesting_fact": "India is the largest democracy in the world."
  },
  {
    "id": 7,
    "country": "South Africa",
    "capital": "Pretoria (administrative)",
    "population": 60400000,
    "interesting_fact": "South Africa has three capital cities."
  },
  {
    "id": 8,
    "country": "Norway",
    "capital": "Oslo",
    "population": 5500000,
    "interesting_fact": "Norway experiences the midnight sun during summer."
  }
]